extrudion/__init__.py
extrudion/analyzers.py
extrudion/extrudion.py
extrudion/files.py
extrudion/fit.py
extrudion/plot.py
extrudion-2.2.1.dist-info/LICENSE
extrudion-2.2.1.dist-info/METADATA
extrudion-2.2.1.dist-info/WHEEL
extrudion-2.2.1.dist-info/RECORD
