Metadata-Version: 2.1
Name: extrudion
Version: 2.2.1
Summary: Analyzes TRA files for stress and strain
License: MIT
Author: Paride Azzari
Author-email: paride21azzari@gmail.com
Requires-Python: >=3.10
Classifier: License :: OSI Approved :: MIT License
Classifier: Programming Language :: Python :: 3
Classifier: Programming Language :: Python :: 3.10
Classifier: Programming Language :: Python :: 3.11
Requires-Dist: colorama (>=0.4.6,<0.5.0)
Requires-Dist: fsspec (>=2025.2.0,<2026.0.0)
Requires-Dist: matplotlib (>=3.10.0,<4.0.0)
Requires-Dist: numpy (>=2.1.0,<3.0.0)
Requires-Dist: pandas (>=2.2.3,<3.0.0)
